[
    {
        "name": "ฝันถึงเรื่องนั้นอีกแล้ว",
        "writer": "Yoru Sumino",
        "img": "https://images-se-ed.com/ws/Storage/Originals/978616/182/9786161824686L.jpg",
        "link": "https://www.se-ed.com/product/%E0%B8%9D%E0%B8%B1%E0%B8%99%E0%B8%96%E0%B8%B6%E0%B8%87%E0%B9%80%E0%B8%A3%E0%B8%B7%E0%B9%88%E0%B8%AD%E0%B8%87%E0%B8%99%E0%B8%B1%E0%B9%89%E0%B8%99%E0%B8%AD%E0%B8%B5%E0%B8%81%E0%B9%81%E0%B8%A5%E0%B9%89%E0%B8%A7.aspx?no=9786161824686"
    },
    {
        "name": "ปาฏิหาริย์แมวลายส้มผู้พิทักษ์หนังสือ",
        "writer": "Sosuke Natsukawa",
        "img": "https://images-se-ed.com/ws/Storage/Thumbnails2/978616/935/9786169352532.JPG",
        "link": "https://www.se-ed.com/product/%E0%B8%9B%E0%B8%B2%E0%B8%8F%E0%B8%B4%E0%B8%AB%E0%B8%B2%E0%B8%A3%E0%B8%B4%E0%B8%A2%E0%B9%8C%E0%B9%81%E0%B8%A1%E0%B8%A7%E0%B8%A5%E0%B8%B2%E0%B8%A2%E0%B8%AA%E0%B9%89%E0%B8%A1%E0%B8%9C%E0%B8%B9%E0%B9%89%E0%B8%9E%E0%B8%B4%E0%B8%97%E0%B8%B1%E0%B8%81%E0%B8%A9%E0%B9%8C%E0%B8%AB%E0%B8%99%E0%B8%B1%E0%B8%87%E0%B8%AA%E0%B8%B7%E0%B8%AD-The-Cat-Who-Loved-to-Protect-Books.aspx?no=9786169352532"
    },
    {
        "name": "โมโม่",
        "writer": "Michael Ende",
        "img": "https://images-se-ed.com/ws/Storage/Originals/978616/184/9786161849887L.jpg",
        "link": "https://www.se-ed.com/product/%E0%B9%82%E0%B8%A1%E0%B9%82%E0%B8%A1%E0%B9%88.aspx?no=9786161849887"
    },
    {
        "name": "แฮร์รี่ พอตเตอร์ กับศิลาอาถรรพ์",
        "writer": "J.K. Rowling",
        "img": "https://images-se-ed.com/ws/Storage/Thumbnails2/978616/044/9786160447473.JPG",
        "link": "https://www.se-ed.com/product/%E0%B9%81%E0%B8%AE%E0%B8%A3%E0%B9%8C%E0%B8%A3%E0%B8%B5%E0%B9%88-%E0%B8%9E%E0%B8%AD%E0%B8%95%E0%B9%80%E0%B8%95%E0%B8%AD%E0%B8%A3%E0%B9%8C-%E0%B8%81%E0%B8%B1%E0%B8%9A%E0%B8%A8%E0%B8%B4%E0%B8%A5%E0%B8%B2%E0%B8%AD%E0%B8%B2%E0%B8%96%E0%B8%A3%E0%B8%A3%E0%B8%9E%E0%B9%8C-%E0%B9%80%E0%B8%A5%E0%B9%88%E0%B8%A1-1-%E0%B8%89%E0%B8%9A%E0%B8%B1%E0%B8%9A%E0%B8%9B%E0%B8%B5-2020.aspx?no=9786160447473"
    },
    {
        "name": "ปาฏิหาริย์ร้านชำของคุณนามิยะ",
        "writer": "Higashino Keigo",
        "img": "https://images-se-ed.com/ws/Storage/Thumbnails2/978616/287/9786162872600.JPG?h=68406d343f90eb2959e0d9ae4ba66137",
        "link": "https://www.se-ed.com/product/%E0%B8%9B%E0%B8%B2%E0%B8%8F%E0%B8%B4%E0%B8%AB%E0%B8%B2%E0%B8%A3%E0%B8%B4%E0%B8%A2%E0%B9%8C%E0%B8%A3%E0%B9%89%E0%B8%B2%E0%B8%99%E0%B8%8A%E0%B8%B3%E0%B8%82%E0%B8%AD%E0%B8%87%E0%B8%84%E0%B8%B8%E0%B8%93%E0%B8%99%E0%B8%B2%E0%B8%A1%E0%B8%B4%E0%B8%A2%E0%B8%B0.aspx?no=9786162872600"
    },
    {
        "name": "ชาร์ล็อตต์ แมงมุมเพื่อนรัก",
        "writer": "E.B. White",
        "img": "https://images-se-ed.com/ws/Storage/Thumbnails2/978974/759/9789747597042.jpg",
        "link": "https://www.se-ed.com/product/%E0%B8%8A%E0%B8%B2%E0%B8%A3%E0%B9%8C%E0%B8%A5%E0%B9%87%E0%B8%AD%E0%B8%95%E0%B8%95%E0%B9%8C-%E0%B9%81%E0%B8%A1%E0%B8%87%E0%B8%A1%E0%B8%B8%E0%B8%A1%E0%B9%80%E0%B8%9E%E0%B8%B7%E0%B9%88%E0%B8%AD%E0%B8%99%E0%B8%A3%E0%B8%B1%E0%B8%81.aspx?no=9789747597042"
    },
    {
        "name": "บ้านเล็กในป่าใหญ่",
        "writer": "ลอร่า อิงกัลล์ส ไวล์เดอร์",
        "img": "https://images-se-ed.com/ws/Storage/Thumbnails2/978974/980/9789749804193.jpg",
        "link": "https://www.se-ed.com/product/%E0%B8%AB%E0%B8%99%E0%B8%B1%E0%B8%87%E0%B8%AA%E0%B8%B7%E0%B8%AD%E0%B8%8A%E0%B8%B8%E0%B8%94%E0%B8%9A%E0%B9%89%E0%B8%B2%E0%B8%99%E0%B9%80%E0%B8%A5%E0%B9%87%E0%B8%81-%E0%B9%80%E0%B8%A5%E0%B9%88%E0%B8%A1-1-%E0%B8%9A%E0%B9%89%E0%B8%B2%E0%B8%99%E0%B9%80%E0%B8%A5%E0%B9%87%E0%B8%81%E0%B9%83%E0%B8%99%E0%B8%9B%E0%B9%88%E0%B8%B2%E0%B9%83%E0%B8%AB%E0%B8%8D%E0%B9%88.aspx?no=9789749804193"
    },
    {
        "name": "แอนิมอล ฟาร์ม",
        "writer": "George Orwell",
        "img": "https://images-se-ed.com/ws/Storage/Thumbnails2/978616/714/9786167144252.JPG",
        "link": "https://www.se-ed.com/product/%E0%B9%81%E0%B8%AD%E0%B8%99%E0%B8%B4%E0%B8%A1%E0%B8%AD%E0%B8%A5-%E0%B8%9F%E0%B8%B2%E0%B8%A3%E0%B9%8C%E0%B8%A1-%E0%B8%AA%E0%B8%87%E0%B8%84%E0%B8%A3%E0%B8%B2%E0%B8%A1%E0%B8%81%E0%B8%9A%E0%B8%8F%E0%B8%82%E0%B8%AD%E0%B8%87%E0%B8%AA%E0%B8%A3%E0%B8%A3%E0%B8%9E%E0%B8%AA%E0%B8%B1%E0%B8%95%E0%B8%A7%E0%B9%8C.aspx?no=9786167144252"
    },
    {
        "name": "เด็กชายมะลิวัลย์",
        "writer": "ประภัสสร เสวิกุล",
        "img": "https://images-se-ed.com/ws/Storage/Thumbnails2/978974/289/9789742894757.jpg",
        "link": "https://www.se-ed.com/product/%E0%B9%80%E0%B8%94%E0%B9%87%E0%B8%81%E0%B8%8A%E0%B8%B2%E0%B8%A2%E0%B8%A1%E0%B8%B0%E0%B8%A5%E0%B8%B4%E0%B8%A7%E0%B8%B1%E0%B8%A5%E0%B8%A2%E0%B9%8C.aspx?no=9789742894757"
    },
    {
        "name": "เจ้าชายน้อย",
        "writer": "Antoine de Saint-Exupery",
        "img": "https://images-se-ed.com/ws/Storage/Thumbnails2/978616/916/9786169160113.jpg",
        "link": "https://www.se-ed.com/product/%E0%B9%80%E0%B8%88%E0%B9%89%E0%B8%B2%E0%B8%8A%E0%B8%B2%E0%B8%A2%E0%B8%99%E0%B9%89%E0%B8%AD%E0%B8%A2.aspx?no=9786169160113"
    },
    {
        "name": "Atomic Habits",
        "writer": "James Clear",
        "img": "https://images-se-ed.com/ws/Storage/Thumbnails2/978616/083/9786160838257.JPG",
        "link": "https://www.se-ed.com/product/Atomic-Habits-%E0%B9%80%E0%B8%9E%E0%B8%A3%E0%B8%B2%E0%B8%B0%E0%B8%8A%E0%B8%B5%E0%B8%A7%E0%B8%B4%E0%B8%95%E0%B8%94%E0%B8%B5%E0%B9%84%E0%B8%94%E0%B9%89%E0%B8%81%E0%B8%A7%E0%B9%88%E0%B8%B2%E0%B8%97%E0%B8%B5%E0%B9%88%E0%B9%80%E0%B8%9B%E0%B9%87%E0%B8%99.aspx?no=9786160838257"
    },
    {
        "name": "Think Again",
        "writer": "Adam Grant",
        "img": "https://images-se-ed.com/ws/Storage/Thumbnails2/978616/287/9786162875045.JPG",
        "link": "https://www.se-ed.com/product/%E0%B8%84%E0%B8%B4%E0%B8%94%E0%B9%81%E0%B8%A5%E0%B9%89%E0%B8%A7-%E0%B8%84%E0%B8%B4%E0%B8%94%E0%B8%AD%E0%B8%B5%E0%B8%81-Think-Again.aspx?no=9786162875045"
    },
    {
        "name": "พลังของคนที่กล้าทำอะไรคนเดียว",
        "writer": "Tokio Godo",
        "img": "https://images-se-ed.com/ws/Storage/Thumbnails2/978616/183/9786161835927.JPG",
        "link": "https://www.se-ed.com/product/%E0%B8%9E%E0%B8%A5%E0%B8%B1%E0%B8%87%E0%B8%82%E0%B8%AD%E0%B8%87%E0%B8%84%E0%B8%99%E0%B8%97%E0%B8%B5%E0%B9%88%E0%B8%81%E0%B8%A5%E0%B9%89%E0%B8%B2%E0%B8%97%E0%B8%B3%E0%B8%AD%E0%B8%B0%E0%B9%84%E0%B8%A3%E0%B8%84%E0%B8%99%E0%B9%80%E0%B8%94%E0%B8%B5%E0%B8%A2%E0%B8%A7.aspx?no=9786161835927"
    },
    {
        "name": "ศิลปะการอยู่ร่วมกับคนเฮงซวย",
        "writer": "Robert Sutton",
        "img": "https://images-se-ed.com/ws/Storage/Thumbnails2/978616/182/9786161825966.JPG",
        "link": "https://www.se-ed.com/product/%E0%B8%A8%E0%B8%B4%E0%B8%A5%E0%B8%9B%E0%B8%B0%E0%B8%81%E0%B8%B2%E0%B8%A3%E0%B8%AD%E0%B8%A2%E0%B8%B9%E0%B9%88%E0%B8%A3%E0%B9%88%E0%B8%A7%E0%B8%A1%E0%B8%81%E0%B8%B1%E0%B8%9A%E0%B8%84%E0%B8%99%E0%B9%80%E0%B8%AE%E0%B8%87%E0%B8%8B%E0%B8%A7%E0%B8%A2.aspx?no=9786161825966"
    },
    {
        "name": "The Little Book of Ikigai",
        "writer": "Ken Mogi",
        "img": "https://images-se-ed.com/ws/Storage/Thumbnails2/978616/084/9786160842551.JPG",
        "link": "https://www.se-ed.com/product/%E0%B8%AD%E0%B8%B4%E0%B8%84%E0%B8%B4%E0%B9%84%E0%B8%81-The-Little-Book-of-Ikigai.aspx?no=9786160842551"
    },
    {
        "name": "Mindset",
        "writer": "Carol S. Dweck",
        "img": "https://images-se-ed.com/ws/Storage/Thumbnails2/978616/287/9786162872655.JPG",
        "link": "https://www.se-ed.com/product/%E0%B9%83%E0%B8%8A%E0%B9%89%E0%B8%84%E0%B8%A7%E0%B8%B2%E0%B8%A1%E0%B8%84%E0%B8%B4%E0%B8%94%E0%B9%80%E0%B8%AD%E0%B8%B2%E0%B8%8A%E0%B8%99%E0%B8%B0%E0%B9%82%E0%B8%8A%E0%B8%84%E0%B8%8A%E0%B8%B0%E0%B8%95%E0%B8%B2-Mindset.aspx?no=9786162872655"
    },
    {
        "name": "อย่าเป็นคนเก่งที่คุยไม่เป็น",
        "writer": "Tadashi Yasuda",
        "img": "https://images-se-ed.com/ws/Storage/Thumbnails2/978616/287/9786162873829.JPG",
        "link": "https://www.se-ed.com/product/%E0%B8%AD%E0%B8%A2%E0%B9%88%E0%B8%B2%E0%B9%80%E0%B8%9B%E0%B9%87%E0%B8%99%E0%B8%84%E0%B8%99%E0%B9%80%E0%B8%81%E0%B9%88%E0%B8%87%E0%B8%97%E0%B8%B5%E0%B9%88%E0%B8%84%E0%B8%B8%E0%B8%A2%E0%B9%84%E0%B8%A1%E0%B9%88%E0%B9%80%E0%B8%9B%E0%B9%87%E0%B8%99.aspx?no=9786162873829"
    },
    {
        "name": "I Want to Eat Your Pancreas",
        "writer": "Yoru Sumino",
        "img": "https://images-se-ed.com/ws/Storage/Originals/978616/371/9786163711038L.jpg?h=44082aa6086a1e34604827210635198f&width=161&hight=250",
        "link": "https://www.se-ed.com/product/%E0%B8%95%E0%B8%B1%E0%B8%9A%E0%B8%AD%E0%B9%88%E0%B8%AD%E0%B8%99%E0%B9%80%E0%B8%98%E0%B8%AD%E0%B8%99%E0%B8%B1%E0%B9%89%E0%B8%99%E0%B8%82%E0%B8%AD%E0%B8%89%E0%B8%B1%E0%B8%99%E0%B9%80%E0%B8%96%E0%B8%AD%E0%B8%B0%E0%B8%99%E0%B8%B0-I-Want-to-Eat-Your-Pancreas.aspx?no=9786163711038"
    },
    {
        "name": "ยิ่งหิวยิ่งอายุยืน",
        "writer": "Yoshinori Nagumo",
        "img": "https://images-se-ed.com/ws/Storage/Thumbnails2/978616/287/9786162872037.jpg",
        "link":"https://www.se-ed.com/product/%E0%B8%A2%E0%B8%B4%E0%B9%88%E0%B8%87%E0%B8%AB%E0%B8%B4%E0%B8%A7%E0%B8%A2%E0%B8%B4%E0%B9%88%E0%B8%87%E0%B8%AD%E0%B8%B2%E0%B8%A2%E0%B8%B8%E0%B8%A2%E0%B8%B7%E0%B8%99.aspx?no=9786162872037"
    }
]